README.rst
setup.py
pure_fasttext/FastText.py
pure_fasttext/__init__.py
pure_fasttext/tests/__init__.py
pure_fasttext/tests/test_supervised.py
pure_fasttext/tests/test_unsupervised.py
pure_predict.egg-info/PKG-INFO
pure_predict.egg-info/SOURCES.txt
pure_predict.egg-info/dependency_links.txt
pure_predict.egg-info/requires.txt
pure_predict.egg-info/top_level.txt
pure_sklearn/__init__.py
pure_sklearn/base.py
pure_sklearn/dummy.py
pure_sklearn/map.py
pure_sklearn/naive_bayes.py
pure_sklearn/pipeline.py
pure_sklearn/utils.py
pure_sklearn/ensemble/__init__.py
pure_sklearn/ensemble/_bagging.py
pure_sklearn/ensemble/_forest.py
pure_sklearn/ensemble/_gb.py
pure_sklearn/ensemble/_gb_losses.py
pure_sklearn/ensemble/tests/__init__.py
pure_sklearn/ensemble/tests/test_bagging.py
pure_sklearn/ensemble/tests/test_extra_trees.py
pure_sklearn/ensemble/tests/test_gb.py
pure_sklearn/ensemble/tests/test_import.py
pure_sklearn/ensemble/tests/test_random_forest.py
pure_sklearn/feature_extraction/__init__.py
pure_sklearn/feature_extraction/_dict_vectorizer.py
pure_sklearn/feature_extraction/_hash.py
pure_sklearn/feature_extraction/text.py
pure_sklearn/feature_extraction/tests/__init__.py
pure_sklearn/feature_extraction/tests/test_dict_vectorizer.py
pure_sklearn/feature_extraction/tests/test_import.py
pure_sklearn/feature_extraction/tests/test_text.py
pure_sklearn/impute/__init__.py
pure_sklearn/impute/_base.py
pure_sklearn/impute/tests/__init__.py
pure_sklearn/impute/tests/test_import.py
pure_sklearn/impute/tests/test_missing_indicator.py
pure_sklearn/impute/tests/test_simple_imputer.py
pure_sklearn/linear_model/__init__.py
pure_sklearn/linear_model/_base.py
pure_sklearn/linear_model/_logistic.py
pure_sklearn/linear_model/_passive_aggressive.py
pure_sklearn/linear_model/_perceptron.py
pure_sklearn/linear_model/_ridge.py
pure_sklearn/linear_model/_stochastic_gradient.py
pure_sklearn/linear_model/tests/__init__.py
pure_sklearn/linear_model/tests/test_import.py
pure_sklearn/linear_model/tests/test_logistic.py
pure_sklearn/linear_model/tests/test_passive_aggressive.py
pure_sklearn/linear_model/tests/test_perceptron.py
pure_sklearn/linear_model/tests/test_ridge.py
