Metadata-Version: 2.1
Name: pure-predict
Version: 0.0.3
Summary: Machine learning prediction in pure Python
Home-page: UNKNOWN
Author: Ibotta Inc.
Author-email: machine_learning@ibotta.com
License: Apache 2.0
Download-URL: https://pypi.org/project/pure-predict/#files
Project-URL: Source Code, https://github.com/Ibotta/pure-predict
Platform: UNKNOWN
Classifier: Intended Audience :: Developers
Classifier: Programming Language :: Python
Classifier: Programming Language :: Python :: 3
Classifier: Programming Language :: Python :: 3.5
Classifier: Programming Language :: Python :: 3.6
Classifier: Programming Language :: Python :: 3.7
Classifier: Programming Language :: Python :: 3.8
Classifier: Topic :: Scientific/Engineering
Requires-Python: >=3.5
Provides-Extra: tests
